phmin/__init__.py
phmin/custom_exceptions.py
phmin/funcs.py
phmin/ls_ph_minner.py
phmin/ph_minner.py
phmin-1.0.0.dist-info/LICENSE
phmin-1.0.0.dist-info/METADATA
phmin-1.0.0.dist-info/WHEEL
phmin-1.0.0.dist-info/top_level.txt
phmin-1.0.0.dist-info/RECORD
