Metadata-Version: 2.1
Name: phmin
Version: 1.0.0
Summary: A basic python package for identifying frequencies present in time series data based on the principles of phase dispersion minimization. 
Home-page: https://www.github.com/erikstacey/phmin
Author: Erik William Stacey
Author-email: Erik Stacey <erik@erikstacey.com>
License: MIT
Project-URL: Homepage, https://github.com/erikstacey/phmin
Project-URL: Bug Tracker, https://github.com/erikstacey/phmin/issues
Classifier: Programming Language :: Python :: 3
Classifier: License :: OSI Approved :: MIT License
Classifier: Operating System :: OS Independent
Requires-Python: >=3.7
License-File: LICENSE
Requires-Dist: numpy
Requires-Dist: matplotlib
Requires-Dist: scipy
